{
  "type": "Feature",
  "properties": {
    "gn:admin1_code":"RE",
    "gn:admin2_code":"974.0",
    "gn:admin3_code":"9741.0",
    "gn:admin4_code":"97418.0",
    "gn:asciiname":"La Reunion",
    "gn:country_code":"RE",
    "gn:dem":54,
    "gn:feature_class":"P",
    "gn:feature_code":"PPL",
    "gn:name":"La R\u00e9union",
    "gn:population":0,
    "gn:timezone":"Indian/Reunion",
    "iso:country":"RE",
    "name:ceb_x_preferred":[
        "La Reunion"
    ],
    "name:fra_x_preferred":[
        "La R\u00e9union"
    ],
    "name:fra_x_variant":[
        "Les Cocos"
    ],
    "name:nld_x_preferred":[
        "La R\u00e9union"
    ],
    "name:srp_x_preferred":[
        "\u041b\u0430 \u0420\u0435\u0443\u043d\u0438\u043e\u043d"
    ],
    "name:swe_x_preferred":[
        "La Reunion"
    ],
    "name:und_x_variant":[
        "R\u00e9union"
    ],
    "wof:name":"La Reunion",
    "wof:placetype":"locality"
},
  "geometry": {"coordinates":[55.5365,-20.90074],"type":"Point"}
}