{
  "type": "Feature",
  "properties": {
    "gn:admin1_code":"RE",
    "gn:admin2_code":"974.0",
    "gn:admin3_code":"9741.0",
    "gn:admin4_code":"97420.0",
    "gn:asciiname":"Commune Begue",
    "gn:country_code":"RE",
    "gn:dem":165,
    "gn:feature_class":"P",
    "gn:feature_code":"PPL",
    "gn:name":"Commune B\u00e8gue",
    "gn:population":0,
    "gn:timezone":"Indian/Reunion",
    "iso:country":"RE",
    "name:fra_x_preferred":[
        "Commune B\u00e8gue"
    ],
    "wof:name":"Commune Begue",
    "wof:placetype":"locality"
},
  "geometry": {"coordinates":[55.62829,-20.95314],"type":"Point"}
}