{
  "type": "Feature",
  "properties": {
    "gn:admin1_code":"RE",
    "gn:admin2_code":"974.0",
    "gn:admin3_code":"9741.0",
    "gn:admin4_code":"97411.0",
    "gn:asciiname":"Saint-Francois",
    "gn:country_code":"RE",
    "gn:dem":387,
    "gn:feature_class":"P",
    "gn:feature_code":"PPL",
    "gn:name":"Saint-Fran\u00e7ois",
    "gn:population":0,
    "gn:timezone":"Indian/Reunion",
    "iso:country":"RE",
    "name:fra_x_preferred":[
        "Saint-Fran\u00e7ois"
    ],
    "wof:name":"Saint-Francois",
    "wof:placetype":"locality"
},
  "geometry": {"coordinates":[55.45891999999999,-20.91702],"type":"Point"}
}