{
  "type": "Feature",
  "properties": {
    "gn:admin1_code":"RE",
    "gn:admin2_code":"974.0",
    "gn:admin3_code":"9742.0",
    "gn:admin4_code":"97416.0",
    "gn:asciiname":"Casabona",
    "gn:country_code":"RE",
    "gn:dem":-9999,
    "gn:feature_class":"P",
    "gn:feature_code":"PPL",
    "gn:name":"Casabona",
    "gn:population":0,
    "gn:timezone":"Indian/Reunion",
    "iso:country":"RE",
    "name:fra_x_preferred":[
        "Casabona"
    ],
    "wof:name":"Casabona",
    "wof:placetype":"locality"
},
  "geometry": {"coordinates":[55.46714,-21.3347],"type":"Point"}
}