{
  "type": "Feature",
  "properties": {
    "gn:admin1_code":"RE",
    "gn:admin2_code":"974.0",
    "gn:admin3_code":"9742.0",
    "gn:admin4_code":"97416.0",
    "gn:asciiname":"Casabona",
    "gn:country_code":"RE",
    "gn:dem":-9999,
    "gn:feature_class":"P",
    "gn:feature_code":"PPL",
    "gn:name":"Casabona",
    "gn:population":0,
    "gn:timezone":"Indian/Reunion",
    "iso:country":"RE",
    "name:azb_x_preferred":[
        "\u06a9\u0627\u0633\u0627\u0628\u0648\u0646\u0627"
    ],
    "name:bcl_x_preferred":[
        "Casabona"
    ],
    "name:bul_x_preferred":[
        "\u041a\u0430\u0437\u0430\u0431\u043e\u043d\u0430"
    ],
    "name:ceb_x_preferred":[
        "Casabona"
    ],
    "name:deu_x_preferred":[
        "Casabona"
    ],
    "name:epo_x_preferred":[
        "Casabona"
    ],
    "name:eus_x_preferred":[
        "Casabona"
    ],
    "name:fas_x_preferred":[
        "\u06a9\u0627\u0633\u0627\u0628\u0648\u0646\u0627"
    ],
    "name:fra_x_preferred":[
        "Casabona"
    ],
    "name:hun_x_preferred":[
        "Casabona"
    ],
    "name:hye_x_preferred":[
        "\u053f\u0561\u0566\u0561\u0562\u0578\u0576\u0561"
    ],
    "name:ina_x_preferred":[
        "Casabona"
    ],
    "name:ita_x_preferred":[
        "Casabona"
    ],
    "name:jpn_x_preferred":[
        "\u30ab\u30b6\u30dc\u30fc\u30ca"
    ],
    "name:kaz_x_preferred":[
        "\u041a\u0430\u0437\u0430\u0431\u043e\u043d\u0430"
    ],
    "name:lat_x_preferred":[
        "Casubonum"
    ],
    "name:lmo_x_preferred":[
        "Casabona"
    ],
    "name:msa_x_preferred":[
        "Casabona"
    ],
    "name:nap_x_preferred":[
        "Casabona"
    ],
    "name:nld_x_preferred":[
        "Casabona"
    ],
    "name:pms_x_preferred":[
        "Casabona"
    ],
    "name:pol_x_preferred":[
        "Casabona"
    ],
    "name:por_x_preferred":[
        "Casabona"
    ],
    "name:ron_x_preferred":[
        "Casabona"
    ],
    "name:rus_x_preferred":[
        "\u041a\u0430\u0437\u0430\u0431\u043e\u043d\u0430"
    ],
    "name:scn_x_preferred":[
        "Casivona"
    ],
    "name:spa_x_preferred":[
        "Casabona"
    ],
    "name:srp_x_preferred":[
        "\u041a\u0430\u0437\u0430\u0431\u043e\u043d\u0430"
    ],
    "name:ukr_x_preferred":[
        "\u041a\u0430\u0437\u0430\u0431\u043e\u043d\u0430"
    ],
    "name:uzb_x_preferred":[
        "Casabona"
    ],
    "name:vie_x_preferred":[
        "Casabona"
    ],
    "name:vol_x_preferred":[
        "Casabona"
    ],
    "name:war_x_preferred":[
        "Casabona"
    ],
    "name:zho_x_preferred":[
        "\u5361\u8428\u535a\u7eb3"
    ],
    "wof:name":"Casabona",
    "wof:placetype":"locality"
},
  "geometry": {"coordinates":[55.46714,-21.3347],"type":"Point"}
}