{
  "type": "Feature",
  "properties": {
    "gn:admin1_code":"RE",
    "gn:admin2_code":"974.0",
    "gn:admin3_code":"9741.0",
    "gn:admin4_code":"97411.0",
    "gn:asciiname":"Bois de Nefles",
    "gn:country_code":"RE",
    "gn:dem":324,
    "gn:feature_class":"P",
    "gn:feature_code":"PPL",
    "gn:name":"Bois de N\u00e8fles",
    "gn:population":0,
    "gn:timezone":"Indian/Reunion",
    "iso:country":"RE",
    "name:fra_x_preferred":[
        "Bois de N\u00e8fles"
    ],
    "wof:name":"Bois de Nefles",
    "wof:placetype":"locality"
},
  "geometry": {"coordinates":[55.47491,-20.91691],"type":"Point"}
}