{
  "type": "Feature",
  "properties": {
    "gn:admin1_code":"RE",
    "gn:admin2_code":"974.0",
    "gn:admin3_code":"9741.0",
    "gn:admin4_code":"97420.0",
    "gn:asciiname":"Bagatelle",
    "gn:country_code":"RE",
    "gn:dem":199,
    "gn:feature_class":"P",
    "gn:feature_code":"PPL",
    "gn:name":"Bagatelle",
    "gn:population":0,
    "gn:timezone":"Indian/Reunion",
    "iso:country":"RE",
    "name:ara_x_preferred":[
        "\u0627\u0644\u0628\u063a\u0627\u062a\u064a\u0644\u0629"
    ],
    "name:cym_x_preferred":[
        "Bagat\u00e9l"
    ],
    "name:fin_x_preferred":[
        "Fortuna"
    ],
    "name:fra_x_preferred":[
        "Bagatelle"
    ],
    "name:ita_x_preferred":[
        "Bagatelle"
    ],
    "wof:name":"Bagatelle",
    "wof:placetype":"locality"
},
  "geometry": {"coordinates":[55.58178,-20.92802],"type":"Point"}
}