{
  "type": "Feature",
  "properties": {
    "gn:admin1_code":"RE",
    "gn:admin2_code":"974.0",
    "gn:admin3_code":"9744.0",
    "gn:admin4_code":"97408.0",
    "gn:asciiname":"Les Deux Bras",
    "gn:country_code":"RE",
    "gn:dem":303,
    "gn:feature_class":"P",
    "gn:feature_code":"PPL",
    "gn:name":"Les Deux Bras",
    "gn:population":0,
    "gn:timezone":"Indian/Reunion",
    "iso:country":"RE",
    "wof:name":"Les Deux Bras",
    "wof:placetype":"locality"
},
  "geometry": {"coordinates":[55.39133,-21.00104],"type":"Point"}
}