{
  "type": "Feature",
  "properties": {
    "gn:admin1_code":"RE",
    "gn:admin2_code":"974.0",
    "gn:admin3_code":"9743.0",
    "gn:admin4_code":"97410.0",
    "gn:asciiname":"Morange",
    "gn:country_code":"RE",
    "gn:dem":172,
    "gn:feature_class":"P",
    "gn:feature_code":"PPL",
    "gn:name":"Morange",
    "gn:population":0,
    "gn:timezone":"Indian/Reunion",
    "iso:country":"RE",
    "name:fra_x_preferred":[
        "Morange"
    ],
    "wof:name":"Morange",
    "wof:placetype":"locality"
},
  "geometry": {"coordinates":[55.7347,-21.09507],"type":"Point"}
}