{
  "type": "Feature",
  "properties": {
    "gn:admin1_code":"RE",
    "gn:admin2_code":"974.0",
    "gn:admin3_code":"9744.0",
    "gn:admin4_code":"97413.0",
    "gn:asciiname":"Le Piton Saint-Leu",
    "gn:country_code":"RE",
    "gn:dem":1,
    "gn:feature_class":"P",
    "gn:feature_code":"PPL",
    "gn:name":"Le Piton Saint-Leu",
    "gn:population":0,
    "gn:timezone":"Indian/Reunion",
    "iso:country":"RE",
    "name:fra_x_preferred":[
        "Le Piton Saint-Leu"
    ],
    "name:und_x_variant":[
        "Piton",
        "Village du Piton"
    ],
    "wof:name":"Le Piton Saint-Leu",
    "wof:placetype":"locality"
},
  "geometry": {"coordinates":[55.31095,-21.21968],"type":"Point"}
}