{
  "type": "Feature",
  "properties": {
    "gn:admin1_code":"RE",
    "gn:admin2_code":"974.0",
    "gn:admin3_code":"9742.0",
    "gn:admin4_code":"97412.0",
    "gn:asciiname":"Jean Petit",
    "gn:country_code":"RE",
    "gn:dem":223,
    "gn:feature_class":"P",
    "gn:feature_code":"PPL",
    "gn:name":"Jean Petit",
    "gn:population":0,
    "gn:timezone":"Indian/Reunion",
    "iso:country":"RE",
    "name:fra_x_preferred":[
        "Jean Petit"
    ],
    "wof:name":"Jean Petit",
    "wof:placetype":"locality"
},
  "geometry": {"coordinates":[55.62903000000001,-21.3386],"type":"Point"}
}