{
  "type": "Feature",
  "properties": {
    "gn:admin1_code":"00",
    "gn:asciiname":"Cascades",
    "gn:country_code":"RE",
    "gn:dem":150,
    "gn:feature_class":"P",
    "gn:feature_code":"PPL",
    "gn:name":"Cascades",
    "gn:population":0,
    "gn:timezone":"Indian/Reunion",
    "iso:country":"RE",
    "name:ceb_x_preferred":[
        "Cascades"
    ],
    "name:deu_x_preferred":[
        "Cascades"
    ],
    "name:fra_x_preferred":[
        "Cascades"
    ],
    "name:glg_x_preferred":[
        "Cascades"
    ],
    "name:ita_x_preferred":[
        "Cascades"
    ],
    "name:nld_x_preferred":[
        "Cascades"
    ],
    "name:nor_x_preferred":[
        "Cascades"
    ],
    "name:pol_x_preferred":[
        "Cascades"
    ],
    "name:slk_x_preferred":[
        "Cascades"
    ],
    "name:swe_x_preferred":[
        "Cascades"
    ],
    "wof:name":"Cascades",
    "wof:placetype":"locality"
},
  "geometry": {"coordinates":[55.83333,-21.15],"type":"Point"}
}