{
  "type": "Feature",
  "properties": {
    "gn:admin1_code":"RE",
    "gn:admin2_code":"974.0",
    "gn:admin3_code":"9742.0",
    "gn:admin4_code":"97404.0",
    "gn:asciiname":"Le Lambert",
    "gn:country_code":"RE",
    "gn:dem":49,
    "gn:feature_class":"P",
    "gn:feature_code":"PPL",
    "gn:name":"Le Lambert",
    "gn:population":0,
    "gn:timezone":"Indian/Reunion",
    "iso:country":"RE",
    "name:fra_x_preferred":[
        "Le Lambert"
    ],
    "wof:name":"Le Lambert",
    "wof:placetype":"locality"
},
  "geometry": {"coordinates":[55.37513000000001,-21.25716],"type":"Point"}
}