{
  "type": "Feature",
  "properties": {
    "gn:admin1_code":"RE",
    "gn:admin2_code":"974.0",
    "gn:admin3_code":"9742.0",
    "gn:admin4_code":"97422.0",
    "gn:asciiname":"La Pointe",
    "gn:country_code":"RE",
    "gn:dem":364,
    "gn:feature_class":"P",
    "gn:feature_code":"PPL",
    "gn:name":"La Pointe",
    "gn:population":0,
    "gn:timezone":"Indian/Reunion",
    "iso:country":"RE",
    "name:fra_x_preferred":[
        "La Pointe"
    ],
    "wof:name":"La Pointe",
    "wof:placetype":"locality"
},
  "geometry": {"coordinates":[55.51767,-21.29573],"type":"Point"}
}