{
  "type": "Feature",
  "properties": {
    "gn:admin1_code":"RE",
    "gn:admin2_code":"974.0",
    "gn:admin3_code":"9742.0",
    "gn:admin4_code":"97416.0",
    "gn:asciiname":"La Cafrine",
    "gn:country_code":"RE",
    "gn:dem":80,
    "gn:feature_class":"P",
    "gn:feature_code":"PPL",
    "gn:name":"La Cafrine",
    "gn:population":0,
    "gn:timezone":"Indian/Reunion",
    "iso:country":"RE",
    "name:fra_x_preferred":[
        "La Cafrine"
    ],
    "name:und_x_variant":[
        "Cafrine"
    ],
    "wof:name":"La Cafrine",
    "wof:placetype":"locality"
},
  "geometry": {"coordinates":[55.51126,-21.35101],"type":"Point"}
}