{
  "type": "Feature",
  "properties": {
    "gn:admin1_code":"RE",
    "gn:admin2_code":"974.0",
    "gn:admin3_code":"9744.0",
    "gn:admin4_code":"97415.0",
    "gn:asciiname":"Bellemene",
    "gn:country_code":"RE",
    "gn:dem":392,
    "gn:feature_class":"P",
    "gn:feature_code":"PPL",
    "gn:name":"Bellem\u00e8ne",
    "gn:population":0,
    "gn:timezone":"Indian/Reunion",
    "iso:country":"RE",
    "name:fra_x_preferred":[
        "Bellem\u00e8ne"
    ],
    "wof:name":"Bellemene",
    "wof:placetype":"locality"
},
  "geometry": {"coordinates":[55.2949,-21.01904],"type":"Point"}
}