{
  "type": "Feature",
  "properties": {
    "gn:admin1_code":"RE",
    "gn:admin2_code":"974.0",
    "gn:admin3_code":"9742.0",
    "gn:admin4_code":"97416.0",
    "gn:asciiname":"La Ravine des Cafres les Hauts",
    "gn:country_code":"RE",
    "gn:dem":145,
    "gn:feature_class":"P",
    "gn:feature_code":"PPL",
    "gn:name":"La Ravine des Cafres les Hauts",
    "gn:population":0,
    "gn:timezone":"Indian/Reunion",
    "iso:country":"RE",
    "name:fra_x_preferred":[
        "La Ravine des Cafres les Hauts"
    ],
    "name:und_x_variant":[
        "Ravine des Cafres-les Hauts"
    ],
    "wof:name":"La Ravine des Cafres les Hauts",
    "wof:placetype":"locality"
},
  "geometry": {"coordinates":[55.51871,-21.33734],"type":"Point"}
}