{
  "type": "Feature",
  "properties": {
    "gn:admin1_code":"RE",
    "gn:admin2_code":"974.0",
    "gn:admin3_code":"9744.0",
    "gn:admin4_code":"97415.0",
    "gn:asciiname":"Les Filaos",
    "gn:country_code":"RE",
    "gn:dem":-9999,
    "gn:feature_class":"P",
    "gn:feature_code":"PPL",
    "gn:name":"Les Filaos",
    "gn:population":0,
    "gn:timezone":"Indian/Reunion",
    "iso:country":"RE",
    "name:fra_x_preferred":[
        "Les Filaos"
    ],
    "name:und_x_variant":[
        "Filaos"
    ],
    "wof:name":"Les Filaos",
    "wof:placetype":"locality"
},
  "geometry": {"coordinates":[55.22493000000001,-21.07583],"type":"Point"}
}