{
  "type": "Feature",
  "properties": {
    "gn:admin1_code":"RE",
    "gn:admin2_code":"974.0",
    "gn:admin3_code":"9744.0",
    "gn:admin4_code":"97408.0",
    "gn:asciiname":"Grand-Place",
    "gn:country_code":"RE",
    "gn:dem":776,
    "gn:feature_class":"P",
    "gn:feature_code":"PPL",
    "gn:name":"Grand-Place",
    "gn:population":0,
    "gn:timezone":"Indian/Reunion",
    "iso:country":"RE",
    "name:fra_x_preferred":[
        "Grand-Place"
    ],
    "name:und_x_variant":[
        "Grande Place"
    ],
    "wof:name":"Grand-Place",
    "wof:placetype":"locality"
},
  "geometry": {"coordinates":[55.41226,-21.04165],"type":"Point"}
}