{
  "type": "Feature",
  "properties": {
    "gn:admin1_code":"RE",
    "gn:admin2_code":"974.0",
    "gn:admin3_code":"9743.0",
    "gn:admin4_code":"97421.0",
    "gn:asciiname":"Fleurs Jaunes les Hauts",
    "gn:country_code":"RE",
    "gn:dem":752,
    "gn:feature_class":"P",
    "gn:feature_code":"PPL",
    "gn:name":"Fleurs Jaunes les Hauts",
    "gn:population":0,
    "gn:timezone":"Indian/Reunion",
    "iso:country":"RE",
    "name:fra_x_preferred":[
        "Fleurs Jaunes les Hauts"
    ],
    "name:und_x_variant":[
        "Fleurs Jaunes-les Hauts"
    ],
    "wof:name":"Fleurs Jaunes les Hauts",
    "wof:placetype":"locality"
},
  "geometry": {"coordinates":[55.53159,-21.01679],"type":"Point"}
}