{
  "type": "Feature",
  "properties": {
    "gn:admin1_code":"RE",
    "gn:admin2_code":"974.0",
    "gn:admin3_code":"9744.0",
    "gn:admin4_code":"97415.0",
    "gn:asciiname":"Le Grand Pourpier",
    "gn:country_code":"RE",
    "gn:dem":93,
    "gn:feature_class":"P",
    "gn:feature_code":"PPL",
    "gn:name":"Le Grand Pourpier",
    "gn:population":0,
    "gn:timezone":"Indian/Reunion",
    "iso:country":"RE",
    "name:fra_x_preferred":[
        "Le Grand Pourpier"
    ],
    "name:und_x_variant":[
        "Le Pourpier"
    ],
    "wof:name":"Le Grand Pourpier",
    "wof:placetype":"locality"
},
  "geometry": {"coordinates":[55.30958,-20.97302],"type":"Point"}
}