{
  "type": "Feature",
  "properties": {
    "gn:admin1_code":"RE",
    "gn:admin2_code":"974.0",
    "gn:admin3_code":"9742.0",
    "gn:admin4_code":"97424.0",
    "gn:asciiname":"Ilet Tommic",
    "gn:country_code":"RE",
    "gn:dem":1085,
    "gn:feature_class":"P",
    "gn:feature_code":"PPL",
    "gn:name":"\u00celet Tommic",
    "gn:population":0,
    "gn:timezone":"Indian/Reunion",
    "iso:country":"RE",
    "wof:name":"Ilet Tommic",
    "wof:placetype":"locality"
},
  "geometry": {"coordinates":[55.46666999999999,-21.15],"type":"Point"}
}