{
  "type": "Feature",
  "properties": {
    "gn:admin1_code":"RE",
    "gn:admin2_code":"974.0",
    "gn:admin3_code":"9742.0",
    "gn:admin4_code":"97422.0",
    "gn:asciiname":"Bourg-Murat",
    "gn:country_code":"RE",
    "gn:dem":1564,
    "gn:feature_class":"P",
    "gn:feature_code":"PPL",
    "gn:name":"Bourg-Murat",
    "gn:population":0,
    "gn:timezone":"Indian/Reunion",
    "iso:country":"RE",
    "name:fra_x_preferred":[
        "Bourg-Murat"
    ],
    "wof:name":"Bourg-Murat",
    "wof:placetype":"locality"
},
  "geometry": {"coordinates":[55.57292,-21.20366],"type":"Point"}
}