{
  "type": "Feature",
  "properties": {
    "gn:admin1_code":"RE",
    "gn:admin2_code":"974.0",
    "gn:admin3_code":"9742.0",
    "gn:admin4_code":"97412.0",
    "gn:asciiname":"La Passerelle",
    "gn:country_code":"RE",
    "gn:dem":284,
    "gn:feature_class":"P",
    "gn:feature_code":"PPL",
    "gn:name":"La Passerelle",
    "gn:population":0,
    "gn:timezone":"Indian/Reunion",
    "iso:country":"RE",
    "name:fra_x_preferred":[
        "La Passerelle"
    ],
    "name:und_x_variant":[
        "La Passarelle"
    ],
    "wof:name":"La Passerelle",
    "wof:placetype":"locality"
},
  "geometry": {"coordinates":[55.64563,-21.34046],"type":"Point"}
}