{
  "type": "Feature",
  "properties": {
    "gn:admin1_code":"RE",
    "gn:admin2_code":"974.0",
    "gn:admin3_code":"9742.0",
    "gn:admin4_code":"97416.0",
    "gn:asciiname":"Conde",
    "gn:country_code":"RE",
    "gn:dem":427,
    "gn:feature_class":"P",
    "gn:feature_code":"PPL",
    "gn:name":"Cond\u00e9",
    "gn:population":0,
    "gn:timezone":"Indian/Reunion",
    "iso:country":"RE",
    "name:cat_x_preferred":[
        "Conde"
    ],
    "name:ceb_x_preferred":[
        "Conde"
    ],
    "name:fra_x_preferred":[
        "Cond\u00e9"
    ],
    "name:ita_x_preferred":[
        "Conde"
    ],
    "name:nld_x_preferred":[
        "Conde"
    ],
    "name:nor_x_preferred":[
        "Conde"
    ],
    "name:pol_x_preferred":[
        "Conde"
    ],
    "name:por_x_preferred":[
        "Conde"
    ],
    "name:spa_x_preferred":[
        "Conde"
    ],
    "name:swe_x_preferred":[
        "Conde"
    ],
    "name:vie_x_preferred":[
        "Conde"
    ],
    "name:vol_x_preferred":[
        "Conde"
    ],
    "wof:name":"Conde",
    "wof:placetype":"locality"
},
  "geometry": {"coordinates":[55.50836,-21.29317],"type":"Point"}
}