{
  "type": "Feature",
  "properties": {
    "gn:admin1_code":"RE",
    "gn:admin2_code":"974.0",
    "gn:admin3_code":"9742.0",
    "gn:admin4_code":"97414.0",
    "gn:asciiname":"Bel-Air",
    "gn:country_code":"RE",
    "gn:dem":-9999,
    "gn:feature_class":"P",
    "gn:feature_code":"PPL",
    "gn:name":"Bel-Air",
    "gn:population":0,
    "gn:timezone":"Indian/Reunion",
    "iso:country":"RE",
    "name:fra_x_preferred":[
        "Bel-Air"
    ],
    "name:und_x_variant":[
        "Bel Air"
    ],
    "wof:name":"Bel-Air",
    "wof:placetype":"locality"
},
  "geometry": {"coordinates":[55.39749000000001,-21.29315],"type":"Point"}
}