{
  "type": "Feature",
  "properties": {
    "gn:admin1_code":"RE",
    "gn:admin2_code":"974.0",
    "gn:admin3_code":"9742.0",
    "gn:admin4_code":"97424.0",
    "gn:asciiname":"Les Aigrettes",
    "gn:country_code":"RE",
    "gn:dem":964,
    "gn:feature_class":"P",
    "gn:feature_code":"PPL",
    "gn:name":"Les Aigrettes",
    "gn:population":0,
    "gn:timezone":"Indian/Reunion",
    "iso:country":"RE",
    "wof:name":"Les Aigrettes",
    "wof:placetype":"locality"
},
  "geometry": {"coordinates":[55.45608000000001,-21.14287],"type":"Point"}
}