{
  "type": "Feature",
  "properties": {
    "gn:admin1_code":"RE",
    "gn:admin2_code":"974.0",
    "gn:admin3_code":"9742.0",
    "gn:admin4_code":"97416.0",
    "gn:asciiname":"Berive les Bas",
    "gn:country_code":"RE",
    "gn:dem":469,
    "gn:feature_class":"P",
    "gn:feature_code":"PPL",
    "gn:name":"B\u00e9rive les Bas",
    "gn:population":0,
    "gn:timezone":"Indian/Reunion",
    "iso:country":"RE",
    "name:fra_x_preferred":[
        "B\u00e9rive les Bas"
    ],
    "name:und_x_variant":[
        "B\u00e9rive-les Bas"
    ],
    "wof:name":"Berive les Bas",
    "wof:placetype":"locality"
},
  "geometry": {"coordinates":[55.52836,-21.31719],"type":"Point"}
}