{
  "type": "Feature",
  "properties": {
    "gn:admin1_code":"RE",
    "gn:admin2_code":"974.0",
    "gn:admin3_code":"9742.0",
    "gn:admin4_code":"97414.0",
    "gn:asciiname":"L'Eperon",
    "gn:country_code":"RE",
    "gn:dem":264,
    "gn:feature_class":"P",
    "gn:feature_code":"PPL",
    "gn:name":"L\u2019\u00c9peron",
    "gn:population":0,
    "gn:timezone":"Indian/Reunion",
    "iso:country":"RE",
    "name:fra_x_preferred":[
        "L\u2019\u00c9peron"
    ],
    "wof:name":"L'Eperon",
    "wof:placetype":"locality"
},
  "geometry": {"coordinates":[55.41291,-21.24715],"type":"Point"}
}