{
  "type": "Feature",
  "properties": {
    "gn:admin1_code":"RE",
    "gn:admin2_code":"974.0",
    "gn:admin3_code":"9744.0",
    "gn:admin4_code":"97415.0",
    "gn:asciiname":"Maison Lelievre",
    "gn:country_code":"RE",
    "gn:dem":1004,
    "gn:feature_class":"P",
    "gn:feature_code":"PPL",
    "gn:name":"Maison Leli\u00e8vre",
    "gn:population":0,
    "gn:timezone":"Indian/Reunion",
    "iso:country":"RE",
    "wof:name":"Maison Lelievre",
    "wof:placetype":"locality"
},
  "geometry": {"coordinates":[55.31667,-21.08333],"type":"Point"}
}