{
  "type": "Feature",
  "properties": {
    "gn:admin1_code":"RE",
    "gn:admin2_code":"974.0",
    "gn:admin3_code":"9741.0",
    "gn:admin4_code":"97420.0",
    "gn:asciiname":"La Vigne",
    "gn:country_code":"RE",
    "gn:dem":45,
    "gn:feature_class":"P",
    "gn:feature_code":"PPL",
    "gn:name":"La Vigne",
    "gn:population":0,
    "gn:timezone":"Indian/Reunion",
    "iso:country":"RE",
    "name:fra_x_preferred":[
        "La Vigne"
    ],
    "wof:name":"La Vigne",
    "wof:placetype":"locality"
},
  "geometry": {"coordinates":[55.61609,-20.92044],"type":"Point"}
}