{
  "type": "Feature",
  "properties": {
    "gn:admin1_code":"RE",
    "gn:admin2_code":"974.0",
    "gn:admin3_code":"9742.0",
    "gn:admin4_code":"97416.0",
    "gn:asciiname":"Pierrefonds",
    "gn:country_code":"RE",
    "gn:dem":31,
    "gn:feature_class":"P",
    "gn:feature_code":"PPL",
    "gn:name":"Pierrefonds",
    "gn:population":0,
    "gn:timezone":"Indian/Reunion",
    "iso:country":"RE",
    "name:ceb_x_preferred":[
        "Pierrefonds"
    ],
    "name:ces_x_preferred":[
        "Pierrefonds"
    ],
    "name:deu_x_preferred":[
        "Pierrefonds"
    ],
    "name:fra_x_preferred":[
        "Pierrefonds"
    ],
    "name:oci_x_preferred":[
        "Pierrefonds"
    ],
    "name:pol_x_preferred":[
        "Pierrefonds"
    ],
    "name:por_x_preferred":[
        "Pierrefonds"
    ],
    "name:rus_x_preferred":[
        "\u041f\u044c\u0435\u0440\u0444\u043e\u043d"
    ],
    "name:slk_x_preferred":[
        "Pierrefonds"
    ],
    "name:swe_x_preferred":[
        "Pierrefonds"
    ],
    "name:und_x_variant":[
        "Pierrefonds Usine"
    ],
    "wof:name":"Pierrefonds",
    "wof:placetype":"locality"
},
  "geometry": {"coordinates":[55.42973000000001,-21.30135],"type":"Point"}
}