{
  "type": "Feature",
  "properties": {
    "gn:admin1_code":"RE",
    "gn:admin2_code":"974.0",
    "gn:admin3_code":"9742.0",
    "gn:admin4_code":"97416.0",
    "gn:asciiname":"Pierrefonds",
    "gn:country_code":"RE",
    "gn:dem":31,
    "gn:feature_class":"P",
    "gn:feature_code":"PPL",
    "gn:name":"Pierrefonds",
    "gn:population":0,
    "gn:timezone":"Indian/Reunion",
    "iso:country":"RE",
    "name:und_x_variant":[
        "Pierrefonds Usine",
        "Pierrefonds"
    ],
    "wof:name":"Pierrefonds",
    "wof:placetype":"locality"
},
  "geometry": {"coordinates":[55.42973000000001,-21.30135],"type":"Point"}
}